ruffruleannotator/__init__.py
ruffruleannotator/main.py
ruffruleannotator/ruffruleannotator.py
ruffruleannotator/rulesets.py
ruffruleannotator-0.1.3.dist-info/LICENSE
ruffruleannotator-0.1.3.dist-info/METADATA
ruffruleannotator-0.1.3.dist-info/WHEEL
ruffruleannotator-0.1.3.dist-info/entry_points.txt
ruffruleannotator-0.1.3.dist-info/top_level.txt
ruffruleannotator-0.1.3.dist-info/RECORD
