Metadata-Version: 2.1
Name: ruffruleannotator
Version: 0.1.3
Summary: Small tool to annotate and sort rule IDs inside a ruff config for better readability.
Author: Y. Lieder
License: MIT License
Project-URL: Repository, https://github.com/ylieder/ruffruleannotator
Keywords: ruff,formatter,annotator
License-File: LICENSE
Requires-Dist: ruff
